circularAlgos/__init__.py
circularAlgos/circular_stat.py
circularAlgos-1.0.3.dist-info/METADATA
circularAlgos-1.0.3.dist-info/RECORD
circularAlgos-1.0.3.dist-info/WHEEL
circularAlgos-1.0.3.dist-info/top_level.txt
