Metadata-Version: 2.1
Name: circularAlgos
Version: 1.0.3
Summary: Package with many functions for circular distributions
Home-page: https://github.com/karthik-sundaram/circularAlgos
Author: Karthik Sundaram
Author-email: karthik.sun95@gmail.com
License: MIT
Keywords: mixture models circular distributions clustering
Platform: UNKNOWN
Classifier: Development Status :: 4 - Beta
Classifier: Intended Audience :: Developers
Classifier: Topic :: Internet
Classifier: License :: OSI Approved :: MIT License
Classifier: Programming Language :: Python
Classifier: Programming Language :: Python :: 2
Classifier: Programming Language :: Python :: 2.6
Classifier: Programming Language :: Python :: 2.7
Classifier: Programming Language :: Python :: 3
Classifier: Programming Language :: Python :: 3.3
Classifier: Programming Language :: Python :: 3.4
Classifier: Programming Language :: Python :: 3.5
Requires-Dist: numpy
